{
    "jobs": [
        {
            "organizationCode": "wanke",
            "submitter": "sunhy",
            "description": "submit job test",
            "parameters": {
                "param1": "p10000",
                "param2": 1
            },
            "status": "submitted",
            "job_id": "5G3J8NMB5ONRCAYET2K5",
            "submit_time": "2023-03-16 16:59:07"
        },
        {
            "organizationCode": "wanke",
            "submitter": "sunhy",
            "description": "submit job test",
            "parameters": {
                "param1": "p10000",
                "param2": 1
            },
            "status": "submitted",
            "job_id": "SRILOC48WRA5UFL2OHUB",
            "submit_time": "2023-03-16 17:03:35"
        },
        {
            "organizationCode": "wanke",
            "submitter": "sunhy",
            "description": "submit job test",
            "parameters": {
                "param1": "p10000",
                "param2": 1
            },
            "status": "submitted",
            "job_id": "T6OS4ED6FGYHAFAOWYXR",
            "submit_time": "2023-03-16 17:04:16"
        },
        {
            "organizationCode": "wanke",
            "submitter": "sunhy",
            "description": "计算A栋成本",
            "parameters": {
                "param1": "test",
                "param2": 1
            },
            "status": "submitted",
            "job_id": "47RXZ9BUTPZYBFM1BLQE",
            "submit_time": "2023-03-16 17:05:09"
        },
        {
            "organizationCode": "wanke",
            "submitter": "sunhy",
            "description": "submit job test",
            "parameters": {
                "param1": "p10000",
                "param2": 1
            },
            "status": "completed",
            "job_id": "GHB2Z8Y9FQXXJN4A3SC4",
            "submit_time": "2023-03-16 17:13:54",
            "error_massage": null,
            "end_time": "2023-03-16 17:35:46"
        },
        {
            "organizationCode": "wanke",
            "submitter": "sunhy",
            "description": "submit job test",
            "parameters": {
                "param1": "p10000",
                "param2": 1
            },
            "status": "completed",
            "job_id": "8UWFX2MKHK3O9MAV4U2O",
            "submit_time": "2023-03-16 17:14:39",
            "error_massage": null,
            "end_time": "2023-03-16 17:35:46"
        },
        {
            "organizationCode": "wanke",
            "submitter": "sunhy",
            "description": "计算A栋成本",
            "parameters": {
                "param1": "test",
                "param2": 1
            },
            "status": "completed",
            "job_id": "6R9L7C48DRVR7Q962LVX",
            "submit_time": "2023-03-16 17:16:46",
            "error_massage": null,
            "end_time": "2023-03-16 17:35:46"
        },
        {
            "organizationCode": "wanke",
            "submitter": "sunhy",
            "description": "计算A栋成本",
            "parameters": {
                "param1": "test",
                "param2": 1
            },
            "status": "completed",
            "job_id": "E1PAP62OU4QCOPDMT0F0",
            "submit_time": "2023-03-16 17:16:47",
            "error_massage": null,
            "end_time": "2023-03-16 17:35:46"
        },
        {
            "organizationCode": "wanke",
            "submitter": "sunhy",
            "description": "计算A栋成本",
            "parameters": {
                "param1": "test",
                "param2": 1
            },
            "status": "completed",
            "job_id": "IV7XE5FOMIC7D6D1L801",
            "submit_time": "2023-03-16 17:16:48",
            "error_massage": null,
            "end_time": "2023-03-16 17:35:46"
        },
        {
            "organizationCode": "wanke",
            "submitter": "sunhy",
            "description": "计算A栋成本",
            "parameters": {
                "param1": "test",
                "param2": 1
            },
            "status": "completed",
            "job_id": "J508F94TW2TWDW848E9T",
            "submit_time": "2023-03-16 17:16:49",
            "error_massage": null,
            "end_time": "2023-03-16 17:35:46"
        },
        {
            "organizationCode": "pariatur ipsum nostrud eiusmod",
            "submitter": "incididunt Ut",
            "description": "occaecat",
            "parameters": {},
            "status": "completed",
            "start_time": "1965-08-06T17:59:28.063Z",
            "end_time": "2023-03-16 21:57:48",
            "error_message": "irure incididunt veniam",
            "job_id": "58QNIR55XSPPJUPKUSKC",
            "submit_time": "2023-03-16 17:40:51",
            "error_massage": null
        },
        {
            "organizationCode": "wanke",
            "submitter": "sunhy",
            "description": "submit job test",
            "parameters": {
                "param1": "p10000",
                "param2": 1
            },
            "status": "completed",
            "job_id": "DTTVB7TKEMR3499B3SZ6",
            "submit_time": "2023-03-16 17:41:02",
            "error_massage": null,
            "end_time": "2023-03-16 21:57:48"
        },
        {
            "organizationCode": "wanke",
            "submitter": "sunhy",
            "description": "submit job test",
            "parameters": {
                "param1": "p10000",
                "param2": 1,
                "param4": 2
            },
            "status": "completed",
            "job_id": "TWLMU4QEKZNGEOI9A9YL",
            "submit_time": "2023-03-16 17:41:18",
            "error_massage": null,
            "end_time": "2023-03-16 21:57:48"
        },
        {
            "organizationCode": "wanke",
            "submitter": "sunhy",
            "description": "submit job test",
            "parameters": {
                "param1": "p10000",
                "param2": 1,
                "param4": 2,
                "param5": 5
            },
            "status": "completed",
            "job_id": "K1JRPHVVDD197F7GQKHC",
            "submit_time": "2023-03-16 17:41:35",
            "error_massage": null,
            "end_time": "2023-03-16 21:57:48"
        },
        {
            "organizationCode": "wanke",
            "submitter": "sunhy",
            "description": "occaecat",
            "parameters": {
                "p1": 1,
                "p2": 2,
                "p3": 5,
                "p4": "wwww"
            },
            "status": "completed",
            "start_time": "1965-08-06T17:59:28.063Z",
            "end_time": "2023-03-16 21:57:48",
            "error_message": "none",
            "job_id": "WDN85IG4MH11DFVN24J4",
            "submit_time": "2023-03-16 17:42:43",
            "error_massage": null
        },
        {
            "organizationCode": "wanke",
            "submitter": "sunhy",
            "description": "计算A栋成本",
            "parameters": {
                "param1": "test",
                "param2": 1
            },
            "status": "completed",
            "job_id": "OCQA5IBWVP7568RYTI05",
            "submit_time": "2023-03-16 17:43:05",
            "error_massage": null,
            "end_time": "2023-03-16 21:57:48"
        },
        {
            "organizationCode": "wanke",
            "submitter": "sunhy",
            "description": "计算A栋成本",
            "parameters": {
                "param1": "test",
                "param2": 1
            },
            "status": "completed",
            "job_id": "K31WSYC3MYG3XU89J40Z",
            "submit_time": "2023-03-16 17:43:06",
            "error_massage": null,
            "end_time": "2023-03-16 21:57:48"
        },
        {
            "organizationCode": "wanke",
            "submitter": "sunhy",
            "description": "计算A栋成本",
            "parameters": {
                "param1": "test",
                "param2": 1
            },
            "status": "completed",
            "job_id": "UQWJDHWZCJHOZ9QT43K0",
            "submit_time": "2023-03-16 17:43:09",
            "error_massage": null,
            "end_time": "2023-03-16 21:57:48"
        },
        {
            "organizationCode": "wanke",
            "submitter": "sunhy",
            "description": "计算A栋成本",
            "parameters": {
                "param1": "test",
                "param2": 1,
                "param3": 3
            },
            "status": "completed",
            "job_id": "J7VQ8PHGXJ24CXXU6BU1",
            "submit_time": "2023-03-16 17:43:36",
            "error_massage": null,
            "end_time": "2023-03-16 21:57:48"
        },
        {
            "organizationCode": "wanke",
            "submitter": "sunhy",
            "description": "计算A栋成本",
            "parameters": {
                "param1": "test",
                "param2": 1,
                "param3": 3
            },
            "status": "completed",
            "job_id": "K5UY38T4CVD66B2NKOYJ",
            "submit_time": "2023-03-16 17:44:23",
            "error_massage": null,
            "end_time": "2023-03-16 21:57:48"
        },
        {
            "organizationCode": "wanke",
            "submitter": "sunhy",
            "description": "计算A栋成本",
            "parameters": {
                "param1": "test",
                "param2": 1,
                "param3": 3
            },
            "status": "completed",
            "job_id": "FMMG9M2WT853UQXRYG81",
            "submit_time": "2023-03-16 17:44:39",
            "error_massage": null,
            "end_time": "2023-03-16 21:57:48"
        },
        {
            "organizationCode": "wanke",
            "submitter": "sunhy",
            "description": "计算A栋成本",
            "parameters": {
                "param1": "test",
                "param2": 1,
                "param3": 3
            },
            "status": "completed",
            "job_id": "Y2Z6M3UZPCOIA1Z4XIXR",
            "submit_time": "2023-03-16 18:35:14",
            "error_massage": null,
            "end_time": "2023-03-16 21:57:48"
        },
        {
            "organizationCode": "wanke",
            "submitter": "sunhy",
            "description": "计算A栋成本",
            "parameters": {
                "param1": "test",
                "param2": 1,
                "param3": 3
            },
            "status": "completed",
            "job_id": "0ARU22VDL4ZQE50UE7I0",
            "submit_time": "2023-03-16 22:00:19",
            "error_massage": null,
            "end_time": "2023-03-16 23:32:23"
        },
        {
            "organizationCode": "wanke",
            "submitter": "sunhy",
            "description": "计算A栋成本",
            "parameters": {
                "param1": "test",
                "param2": 1,
                "param3": 3
            },
            "status": "completed",
            "job_id": "WIB6G3OBPVLCAIA0RUTG",
            "submit_time": "2023-03-16 22:04:31",
            "error_massage": null,
            "end_time": "2023-03-16 23:32:23"
        },
        {
            "organizationCode": "wanke",
            "submitter": "sunhy",
            "description": "计算A栋成本",
            "parameters": {
                "param1": "test",
                "param2": 1,
                "param3": 3
            },
            "status": "completed",
            "job_id": "JZ88LRKUO4BBBR7EA1IV",
            "submit_time": "2023-03-16 23:41:51",
            "error_massage": null,
            "end_time": "2023-03-16 23:44:30"
        },
        {
            "organizationCode": "wanke",
            "submitter": "sunhy",
            "description": "计算A栋成本",
            "parameters": {
                "param1": "test",
                "param2": 1,
                "param3": 3
            },
            "status": "completed",
            "job_id": "T8N76AGUD8BL7HJN2Z4F",
            "submit_time": "2023-03-16 23:43:28",
            "error_massage": null,
            "end_time": "2023-03-16 23:44:30"
        },
        {
            "organizationCode": "wanke",
            "submitter": "sunhy",
            "description": "计算A栋成本",
            "parameters": {
                "param1": "test",
                "param2": 1,
                "param3": 3
            },
            "status": "completed",
            "job_id": "DCK2QDWDHLMVZLGEXQJQ",
            "submit_time": "2023-03-17 00:00:24",
            "error_massage": null,
            "end_time": "2023-03-17 09:08:45"
        },
        {
            "organizationCode": "wanke",
            "submitter": "sunhy",
            "description": "计算A栋成本",
            "parameters": {
                "param1": "test",
                "param2": 1,
                "param3": 3
            },
            "status": "completed",
            "job_id": "KFUZ5W6OEDPVWMA6GSSU",
            "submit_time": "2023-03-17 09:09:42",
            "error_massage": null,
            "end_time": "2023-03-20 14:07:07"
        },
        {
            "organizationCode": "wanke",
            "submitter": "sunhy",
            "description": "计算A栋成本",
            "parameters": {
                "param1": "test",
                "param2": 1,
                "param3": 3
            },
            "status": "completed",
            "job_id": "PFI0E45288FQO6TN6CO1",
            "submit_time": "2023-03-17 09:13:18",
            "error_massage": null,
            "end_time": "2023-03-20 14:07:07"
        },
        {
            "organizationCode": "sed velit ex labore sit",
            "submitter": "laboris pariatur aliqua",
            "description": "deserunt enim labore sunt consectetur",
            "parameters": {},
            "status": "completed",
            "job_id": "43UBU6SAAL89F7T6OJ8N",
            "submit_time": "2023-03-17 10:15:17",
            "error_massage": null,
            "end_time": "2023-03-20 14:07:07"
        },
        {
            "organizationCode": "sed velit ex labore sit",
            "submitter": "laboris pariatur aliqua",
            "description": "deserunt enim labore sunt consectetur",
            "parameters": {},
            "status": "completed",
            "job_id": "W7R0HFSNK4VNLGQ0BWUV",
            "submit_time": "2023-03-17 10:15:22",
            "error_massage": null,
            "end_time": "2023-03-20 14:07:07"
        },
        {
            "organizationCode": "sed velit ex labore sit",
            "submitter": "laboris pariatur aliqua",
            "description": "deserunt enim labore sunt consectetur2",
            "parameters": {},
            "status": "completed",
            "job_id": "TAWUWBC11EBEWJ560VNK",
            "submit_time": "2023-03-17 10:15:29",
            "error_massage": null,
            "end_time": "2023-03-20 14:07:07"
        },
        {
            "organizationCode": "wanke",
            "submitter": "sunhy",
            "description": "计算A栋成本",
            "parameters": {
                "param1": "test",
                "param2": 1,
                "param3": 3
            },
            "status": "completed",
            "job_id": "X2HVU7K0C3YSXSRG9WX6",
            "submit_time": "2023-03-17 16:01:46",
            "error_massage": null,
            "end_time": "2023-03-20 14:07:07"
        },
        {
            "organizationCode": "wanke",
            "submitter": "sunhy",
            "description": "计算A栋成本",
            "parameters": {
                "param1": "test",
                "param2": 1,
                "param3": 3
            },
            "status": "completed",
            "job_id": "YWM4Y3TW2HWX864ZYFIQ",
            "submit_time": "2023-03-19 21:08:06",
            "error_massage": null,
            "end_time": "2023-03-20 14:07:07"
        },
        {
            "organizationCode": "quis",
            "submitter": "veniam dolor consequa",
            "description": "ex commodo",
            "parameters": {},
            "status": "completed",
            "submit_time": "2023-03-20 09:54:12",
            "end_time": "2023-03-20 14:07:07",
            "job_id": "EYEO7QN9C4F3MLDTO75A",
            "error_massage": null
        },
        {
            "organizationCode": "wanke",
            "submitter": "sunhy",
            "description": "计算A栋成本",
            "parameters": {
                "param1": "test",
                "param2": 1,
                "param3": 3
            },
            "status": "completed",
            "job_id": "QBS8D73IXWUBN3GDG2KA",
            "submit_time": "2023-03-20 11:57:32",
            "error_massage": null,
            "end_time": "2023-03-20 14:07:07"
        },
        {
            "organizationCode": "wanke",
            "submitter": "sunhy",
            "description": "计算A栋成本",
            "parameters": {
                "param1": "test",
                "param2": 1,
                "param3": 3
            },
            "status": "completed",
            "job_id": "YOITFVZPYO8Y00OZJEX3",
            "submit_time": "2023-03-20 15:24:38",
            "error_massage": null,
            "end_time": "2023-03-20 19:46:39"
        },
        {
            "organizationCode": "wanke",
            "submitter": "sunhy",
            "description": "计算A栋成本",
            "parameters": {},
            "status": "completed",
            "job_id": "ZO7YD5EU9BH5H5X38LMW",
            "submit_time": "2023-03-20 19:55:50",
            "error_massage": null,
            "end_time": "2023-03-21 08:44:48"
        },
        {
            "organizationCode": "wanke",
            "submitter": "sunhy",
            "description": "计算A栋成本",
            "parameters": {},
            "status": "completed",
            "job_id": "APWT7LK8EW1UBOVGXA15",
            "submit_time": "2023-03-20 19:55:54",
            "error_massage": null,
            "end_time": "2023-03-21 08:44:48"
        },
        {
            "organizationCode": "wanke",
            "submitter": "sunhy",
            "description": "计算A栋成本",
            "parameters": {
                "param1": "test",
                "param2": 1,
                "param3": 3
            },
            "status": "completed",
            "job_id": "14X6YEF40TF4Q5M1SRRN",
            "submit_time": "2023-03-21 16:00:49",
            "error_massage": null,
            "end_time": "2023-03-21 19:32:04"
        },
        {
            "organizationCode": "wanke",
            "submitter": "sunhy",
            "description": "计算A栋成本",
            "parameters": {
                "param1": "test",
                "param2": 1,
                "param3": 3
            },
            "status": "completed",
            "job_id": "A8IUR9PK72LTC9QJQ1MR",
            "submit_time": "2023-03-22 10:19:27",
            "error_massage": null,
            "end_time": "2023-03-22 18:45:13"
        },
        {
            "organizationCode": "wanke",
            "submitter": "zhoufang",
            "description": "计算A栋成本",
            "parameters": {},
            "status": "completed",
            "job_id": "A3RHG09ZNFWT6OZTQ4KX",
            "submit_time": "2023-03-22 10:19:48",
            "error_massage": null,
            "end_time": "2023-03-22 18:45:13"
        },
        {
            "organizationCode": "wanke",
            "submitter": "sunhy",
            "description": "计算A栋成本222",
            "parameters": {
                "param1": "test",
                "param2": 1,
                "param3": 3
            },
            "status": "completed",
            "job_id": "Z8HB5HZEIJWGVR4XJ9QH",
            "submit_time": "2023-03-23 11:31:36",
            "error_massage": null,
            "end_time": "2023-03-24 09:15:15"
        },
        {
            "projectId": "proj002",
            "organizationCode": "wanke",
            "submitter": "zhoufang",
            "description": "zhoufang-test",
            "parameters": {
                "param1": "test",
                "param2": 1,
                "param3": 3
            },
            "status": "completed",
            "job_id": "WLU9OYE1PTGD0S2Z9GWC",
            "submit_time": "2023-03-23 11:32:51",
            "error_massage": null,
            "end_time": "2023-03-24 09:15:15"
        },
        {
            "projectId": "proj002",
            "organizationCode": "wanke",
            "submitter": "zhoufang",
            "description": "zhoufang-test",
            "parameters": {
                "param1": "test",
                "param2": 1,
                "param3": 3
            },
            "status": "completed",
            "job_id": "TV5J4TLNY4YYKY0O50XX",
            "submit_time": "2023-03-23 11:38:55",
            "error_massage": null,
            "end_time": "2023-03-24 09:15:15"
        },
        {
            "projectId": "proj002",
            "organizationCode": "wanke",
            "submitter": "zhoufang",
            "description": "zhoufang-test66666",
            "parameters": {
                "param1": "test",
                "param2": 1,
                "param3": 3
            },
            "status": "completed",
            "job_id": "U4A7J7E73ERMCO9664FW",
            "submit_time": "2023-03-23 11:39:05",
            "error_massage": null,
            "end_time": "2023-03-24 09:15:15"
        },
        {
            "projectId": "proj002",
            "organizationCode": "wanke",
            "submitter": "zhoufang111",
            "description": "zhoufang111",
            "parameters": {
                "param1": "test",
                "param2": 1,
                "param3": 3
            },
            "status": "completed",
            "job_id": "RCSTZ5CU8T7GRJLLW1TB",
            "submit_time": "2023-03-23 11:41:49",
            "error_massage": null,
            "end_time": "2023-03-24 09:15:15"
        },
        {
            "projectId": "proj002",
            "organizationCode": "wanke",
            "submitter": "jjj",
            "description": "jjj",
            "parameters": {
                "param1": "test",
                "param2": 1,
                "param3": 3
            },
            "status": "completed",
            "job_id": "RONEKXVJ8XIDNT7YHTL9",
            "submit_time": "2023-03-23 11:44:07",
            "error_massage": null,
            "end_time": "2023-03-24 09:15:15"
        },
        {
            "projectId": "proj002",
            "organizationCode": "wanke",
            "submitter": "ggg",
            "description": "ggg",
            "parameters": {
                "param1": "test",
                "param2": 1,
                "param3": 3
            },
            "status": "completed",
            "job_id": "IAOCDMRKFM3KGUCYAMEM",
            "submit_time": "2023-03-23 11:46:28",
            "error_massage": null,
            "end_time": "2023-03-24 09:15:15"
        },
        {
            "projectId": "proj002",
            "organizationCode": "wanke",
            "submitter": "fff",
            "description": "fff",
            "parameters": {
                "param1": "test",
                "param2": 1,
                "param3": 3
            },
            "status": "completed",
            "job_id": "QJS0YDTLP9HOZX7PDUWT",
            "submit_time": "2023-03-23 11:46:51",
            "error_massage": null,
            "end_time": "2023-03-24 09:15:15"
        },
        {
            "projectId": "proj002",
            "organizationCode": "wanke",
            "submitter": "dd",
            "description": "dd",
            "parameters": {
                "param1": "test",
                "param2": 1,
                "param3": 3
            },
            "status": "completed",
            "job_id": "Y5SY5R70TYQ59YEVIP6Z",
            "submit_time": "2023-03-23 11:51:58",
            "error_massage": null,
            "end_time": "2023-03-24 09:15:15"
        },
        {
            "projectId": "proj002",
            "organizationCode": "wanke",
            "submitter": "dd",
            "description": "dd",
            "parameters": {
                "param1": "test",
                "param2": 1,
                "param3": 3
            },
            "status": "completed",
            "job_id": "9VVB72J56LBB616LRWWR",
            "submit_time": "2023-03-23 11:52:25",
            "error_massage": null,
            "end_time": "2023-03-24 09:15:15"
        },
        {
            "projectId": "proj002",
            "organizationCode": "wanke",
            "submitter": "ss",
            "description": "ss",
            "parameters": {
                "param1": "test",
                "param2": 1,
                "param3": 3
            },
            "status": "completed",
            "job_id": "3HBXU303YT5XB0DG0G3F",
            "submit_time": "2023-03-23 11:53:01",
            "error_massage": null,
            "end_time": "2023-03-24 09:15:15"
        },
        {
            "organizationCode": "wanke",
            "submitter": "sunhy",
            "description": "计算A栋成本",
            "parameters": {
                "param1": "test",
                "param2": 1,
                "param3": 3
            },
            "status": "completed",
            "job_id": "VNSQH40ALMJ3IOHRYR73",
            "submit_time": "2023-03-23 14:26:42",
            "error_massage": null,
            "end_time": "2023-03-24 09:15:15"
        },
        {
            "projectId": "proj002",
            "organizationCode": "wanke",
            "submitter": "aaa",
            "description": "aaa",
            "parameters": {
                "param1": "test",
                "param2": 1,
                "param3": 3
            },
            "status": "completed",
            "job_id": "DX8BU46SO18M28RWULL9",
            "submit_time": "2023-03-23 16:47:48",
            "error_massage": null,
            "end_time": "2023-03-24 09:15:15"
        },
        {
            "projectId": "proj002",
            "organizationCode": "wanke",
            "submitter": "nnn",
            "description": "nnn",
            "parameters": {
                "param1": "test",
                "param2": 1,
                "param3": 3
            },
            "status": "completed",
            "job_id": "H8OWLR5B2GFID3X1RO9M",
            "submit_time": "2023-03-23 16:48:41",
            "error_massage": null,
            "end_time": "2023-03-24 09:15:15"
        },
        {
            "projectId": "proj002",
            "organizationCode": "wanke",
            "submitter": "bbb",
            "description": "bbb",
            "parameters": {
                "param1": "test",
                "param2": 1,
                "param3": 3
            },
            "status": "completed",
            "job_id": "HPYOOEDA8XUYIF66B8NJ",
            "submit_time": "2023-03-23 16:52:21",
            "error_massage": null,
            "end_time": "2023-03-24 09:15:16"
        }
    ]
}